Metadata-Version: 2.1
Name: pydioc
Version: 0.1
Summary: Python DI/IoC container
Home-page: https://github.com/jaymecd/pydioc
Author: Nikolai Zujev
Author-email: nikolai.zujev@gmail.com
License: UNKNOWN
Project-URL: Repository, https://github.com/jaymecd/pydioc
Project-URL: Bug Reports, https://github.com/jaymecd/pydioc/issues
Project-URL: Documentation, https://github.com/jaymecd/pydioc
Keywords: dependency injection ioc container
Platform: UNKNOWN
Classifier: License :: OSI Approved :: MIT License
Classifier: Development Status :: 4 - Beta
Classifier: Intended Audience :: Developers
Classifier: Natural Language :: English
Classifier: Programming Language :: Python :: 3.7
Classifier: Programming Language :: Python :: 3.8
Requires-Python: >3.7
Provides-Extra: test
